sentida/__init__.py
sentida/__main__.py
sentida/aarup.csv
sentida/intensifier.csv
sentida-0.5.1.dist-info/LICENSE.txt
sentida-0.5.1.dist-info/METADATA
sentida-0.5.1.dist-info/WHEEL
sentida-0.5.1.dist-info/top_level.txt
sentida-0.5.1.dist-info/RECORD
