Metadata-Version: 2.1
Name: sentida
Version: 0.5.1
Summary: The Sentida Danish sentiment analysis package
Home-page: https://github.com/guscode/sentida
Author: Esben Kran, Søren Orm, Jacob Aarup Dalsgaard, Gustav Aarup Lauridsen, Lars Kjartan Bacher Svendsen
Author-email: contact@esbenkc.com
License: CCBY-NC 3.0
Keywords: Natural Language Processing Sentiment Analysis
Platform: UNKNOWN
Classifier: Programming Language :: Python :: 3
Classifier: Operating System :: OS Independent
Classifier: Development Status :: 4 - Beta
Classifier: Intended Audience :: Science/Research
Classifier: Topic :: Scientific/Engineering
